m2dtools/basic/__init__.py
m2dtools/basic/basic.py
m2dtools/basic/dynamics.py
m2dtools/basic/plot.py
m2dtools/basic/structure.py
m2dtools/cg/__init__.py
m2dtools/cg/tools_CG_polymer.py
m2dtools/cg/IBI/IBI.py
m2dtools/cg/IBI/IBI_combine.py
m2dtools/cg/IBI/IBI_modify.py
m2dtools/cg/IBI/IBI_water.py
m2dtools/cg/IBI/get_str.py
m2dtools/cg/IBI/AA/prep_cg.py
m2dtools/lmp/__init__.py
m2dtools/lmp/tools_lammps.py
m2dtools/network/generate_network.py
m2dtools/network/shortest_path.py
m2dtools/other/common.py
m2dtools/other/extract_local_str.py
m2dtools/other/tools_CGwater.py
m2dtools/other/tools_gro.py
m2dtools/other/tools_local_stress.py
m2dtools/other/tools_sio2.py
m2dtools/other/tools_tio2.py
m2dtools-0.1.0.dist-info/METADATA
m2dtools-0.1.0.dist-info/WHEEL
m2dtools-0.1.0.dist-info/top_level.txt
m2dtools-0.1.0.dist-info/RECORD
