Metadata-Version: 2.1
Name: m2dtools
Version: 0.1.0
Summary: Multiscale MD tools: pre/post-processing for molecular dynamics simulations
Author: Zheng Yu, CZ
License: MIT License
Project-URL: Homepage, https://github.com/zyumse/m2dtools
Project-URL: Documentation, https://zyumse.github.io/m2dtools/
Project-URL: Source, https://github.com/zyumse/m2dtools
Requires-Python: >=3.8
Requires-Dist: numpy
Requires-Dist: matplotlib
Requires-Dist: scipy
Requires-Dist: pandas
